shangyun_scrapy_lib/__init__.py
shangyun_scrapy_lib/BaseItems/__init__.py
shangyun_scrapy_lib/BaseItems/base_item.py
shangyun_scrapy_lib/constants/DataType.py
shangyun_scrapy_lib/constants/DictKey.py
shangyun_scrapy_lib/constants/TaskStatistic.py
shangyun_scrapy_lib/constants/TaskStatus.py
shangyun_scrapy_lib/constants/__init__.py
shangyun_scrapy_lib/middlewares/ProcessRequests.py
shangyun_scrapy_lib/middlewares/TaskStatistic.py
shangyun_scrapy_lib/middlewares/TaskStatus.py
shangyun_scrapy_lib/middlewares/Update.py
shangyun_scrapy_lib/middlewares/__init__.py
shangyun_scrapy_lib/pipelines/SavePipeline.py
shangyun_scrapy_lib/pipelines/__init__.py
shangyun_scrapy_lib/scrapy_redis/__init__.py
shangyun_scrapy_lib/scrapy_redis/connection.py
shangyun_scrapy_lib/scrapy_redis/defaults.py
shangyun_scrapy_lib/scrapy_redis/dupefilter.py
shangyun_scrapy_lib/scrapy_redis/filter.py
shangyun_scrapy_lib/scrapy_redis/picklecompat.py
shangyun_scrapy_lib/scrapy_redis/pipelines.py
shangyun_scrapy_lib/scrapy_redis/queue.py
shangyun_scrapy_lib/scrapy_redis/scheduler.py
shangyun_scrapy_lib/scrapy_redis/spiders.py
shangyun_scrapy_lib/scrapy_redis/utils.py
shangyun_scrapy_lib/utils/MongoUtils.py
shangyun_scrapy_lib/utils/RedisUtils.py
shangyun_scrapy_lib/utils/Serialize.py
shangyun_scrapy_lib/utils/TimeUtils.py
shangyun_scrapy_lib/utils/__init__.py
shangyun_scrapy_lib/utils/default.py
shangyun_scrapy_lib/utils/requests.py
shangyun_scrapy_lib/utils/response.py
shangyun_scrapy_lib-0.8.30.dev0.dist-info/METADATA
shangyun_scrapy_lib-0.8.30.dev0.dist-info/WHEEL
shangyun_scrapy_lib-0.8.30.dev0.dist-info/top_level.txt
shangyun_scrapy_lib-0.8.30.dev0.dist-info/RECORD
