Metadata-Version: 2.1
Name: shangyun-scrapy-lib
Version: 0.8.30.dev0
Summary: This is a service of redis subscripe
Home-page: https://ssl.xxx.org/redmine/projects/RedisRun
Author: Andreas Schroeder
Author-email: andreas@drqueue.org
License: GPLv3
Keywords: redis subscripe
Platform: UNKNOWN
Classifier: Development Status :: 3 - Alpha
Classifier: Topic :: Utilities
Classifier: License :: OSI Approved :: GNU General Public License (GPL)
Requires-Dist: Scrapy (>=1.0)
Requires-Dist: redis (>=2.10)
Requires-Dist: six (>=1.5.2)
Requires-Dist: pytz (>=2018.5)
